{
  "data": [
	  {
	    "img":"img/jiaotongzhinan.jpg"
	   
	  },
	  {
	    "img":"img/tuijianluxian.jpg"
	   
	  }, 
	  {
	    "img": "img/yanchushijian.jpg"
	   

	  },
	  {
	    "img": "img/jiaotongzhinan.jpg"
	   
	  },
	  {
	    "img": "img/tuijianluxian.jpg"
	   
	  }, 
	  {
	    "img": "img/yanchushijian.jpg"
	   

	  },
	  {
	    "img": "img/jiaotongzhinan.jpg"
	   
	  },
	  {
	    "img": "img/tuijianluxian.jpg"
	   
	  }, 
	  {
	    "img": "img/yanchushijian.jpg"
	   

	  },
	  {
	    "img": "img/jiaotongzhinan.jpg"
	   
	  },
	  {
	    "img": "img/tuijianluxian.jpg"
	   
	  }, 
	  {
	    "img": "img/yanchushijian.jpg"
	   

	  }
	  ],
 "tab": [
      {
	    "em": "img/pic30.png",
	    "c": "img/pic36.png"
   
      }, 
      {
	     "em": "img/pic33.png",    
	     "c": "img/pic1.jpg"
   
     },
     {
	     "em": "img/pic34.png",
	     "c": "img/pic1.jpg"
   
     }, 
     {
	      "em": "img/pic32.png",
	      "c": "img/pic1.jpg"
   
     },
     {
	     "em": "img/pic31.png",
	     "c": "img/pic1.jpg"
  
     },
     {
	     "em": "img/pic33.png",
	     "c": "img/pic1.jpg"
   
     }
  ]
}
